Workbook

Sheet 说明
A1: Excel 365增强版：使用XLOOKUP/UNIQUE/VSTACK/IFS/动态数组。
A2: 将本模板与 AQ_2020.xlsx…AQ_2024.xlsx 放同一文件夹，均含表‘原始数据’并按模板列。

Sheet 汇总
B1: 贷款总额 | G1: 逾期 | L1: 不良 | Q1: 关注 | V1: 新发生不良 | AA1: 逾期率 | AF1: 不良率 | AK1: 关注率 | AP1: 覆盖率
A2: 银行 | B2: 2020 | C2: 2021 | D2: 2022 | E2: 2023 | F2: 2024 | G2: 2020 | H2: 2021 | I2: 2022 | J2: 2023 | K2: 2024 | L2: 2020 | M2: 2021 | N2: 2022 | O2: 2023 | P2: 2024 | Q2: 2020 | R2: 2021 | S2: 2022 | T2: 2023 | U2: 2024 | V2: 2020 | W2: 2021 | X2: 2022 | Y2: 2023 | Z2: 2024 | AA2: 2020 | AB2: 2021 | AC2: 2022 | AD2: 2023 | AE2: 2024 | AF2: 2020 | AG2: 2021 | AH2: 2022 | AI2: 2023 | AJ2: 2024 | AK2: 2020 | AL2: 2021 | AM2: 2022 | AN2: 2023 | AO2: 2024 | AP2: 2020 | AQ2: 2021 | AR2: 2022 | AS2: 2023 | AT2: 2024
A3: =SORT(UNIQUE(VSTACK('[AQ_2020.xlsx]原始数据'!A:A,'[AQ_2021.xlsx]原始数据'!A:A,'[AQ_2022.xlsx]原始数据'!A:A,'[AQ_2023.xlsx]原始数据'!A:A,'[AQ_2024.xlsx]原始数据'!A:A))) | B3: =XLOOKUP($A3#,'[AQ_2020.xlsx]原始数据'!$A:$A,'[AQ_2020.xlsx]原始数据'!$B:$B,"") | C3: =XLOOKUP($A3#,'[AQ_2021.xlsx]原始数据'!$A:$A,'[AQ_2021.xlsx]原始数据'!$B:$B,"") | D3: =XLOOKUP($A3#,'[AQ_2022.xlsx]原始数据'!$A:$A,'[AQ_2022.xlsx]原始数据'!$B:$B,"") | E3: =XLOOKUP($A3#,'[AQ_2023.xlsx]原始数据'!$A:$A,'[AQ_2023.xlsx]原始数据'!$B:$B,"") | F3: =XLOOKUP($A3#,'[AQ_2024.xlsx]原始数据'!$A:$A,'[AQ_2024.xlsx]原始数据'!$B:$B,"") | G3: =XLOOKUP($A3#,'[AQ_2020.xlsx]原始数据'!$A:$A,'[AQ_2020.xlsx]原始数据'!$C:$C,"") | H3: =XLOOKUP($A3#,'[AQ_2021.xlsx]原始数据'!$A:$A,'[AQ_2021.xlsx]原始数据'!$C:$C,"") | I3: =XLOOKUP($A3#,'[AQ_2022.xlsx]原始数据'!$A:$A,'[AQ_2022.xlsx]原始数据'!$C:$C,"") | J3: =XLOOKUP($A3#,'[AQ_2023.xlsx]原始数据'!$A:$A,'[AQ_2023.xlsx]原始数据'!$C:$C,"") | K3: =XLOOKUP($A3#,'[AQ_2024.xlsx]原始数据'!$A:$A,'[AQ_2024.xlsx]原始数据'!$C:$C,"") | L3: =XLOOKUP($A3#,'[AQ_2020.xlsx]原始数据'!$A:$A,'[AQ_2020.xlsx]原始数据'!$D:$D,"") | M3: =XLOOKUP($A3#,'[AQ_2021.xlsx]原始数据'!$A:$A,'[AQ_2021.xlsx]原始数据'!$D:$D,"") | N3: =XLOOKUP($A3#,'[AQ_2022.xlsx]原始数据'!$A:$A,'[AQ_2022.xlsx]原始数据'!$D:$D,"") | O3: =XLOOKUP($A3#,'[AQ_2023.xlsx]原始数据'!$A:$A,'[AQ_2023.xlsx]原始数据'!$D:$D,"") | P3: =XLOOKUP($A3#,'[AQ_2024.xlsx]原始数据'!$A:$A,'[AQ_2024.xlsx]原始数据'!$D:$D,"") | Q3: =XLOOKUP($A3#,'[AQ_2020.xlsx]原始数据'!$A:$A,'[AQ_2020.xlsx]原始数据'!$E:$E,"") | R3: =XLOOKUP($A3#,'[AQ_2021.xlsx]原始数据'!$A:$A,'[AQ_2021.xlsx]原始数据'!$E:$E,"") | S3: =XLOOKUP($A3#,'[AQ_2022.xlsx]原始数据'!$A:$A,'[AQ_2022.xlsx]原始数据'!$E:$E,"") | T3: =XLOOKUP($A3#,'[AQ_2023.xlsx]原始数据'!$A:$A,'[AQ_2023.xlsx]原始数据'!$E:$E,"") | U3: =XLOOKUP($A3#,'[AQ_2024.xlsx]原始数据'!$A:$A,'[AQ_2024.xlsx]原始数据'!$E:$E,"") | V3: =XLOOKUP($A3#,'[AQ_2020.xlsx]原始数据'!$A:$A,'[AQ_2020.xlsx]原始数据'!$F:$F,"") | W3: =XLOOKUP($A3#,'[AQ_2021.xlsx]原始数据'!$A:$A,'[AQ_2021.xlsx]原始数据'!$F:$F,"") | X3: =XLOOKUP($A3#,'[AQ_2022.xlsx]原始数据'!$A:$A,'[AQ_2022.xlsx]原始数据'!$F:$F,"") | Y3: =XLOOKUP($A3#,'[AQ_2023.xlsx]原始数据'!$A:$A,'[AQ_2023.xlsx]原始数据'!$F:$F,"") | Z3: =XLOOKUP($A3#,'[AQ_2024.xlsx]原始数据'!$A:$A,'[AQ_2024.xlsx]原始数据'!$F:$F,"") | AA3: =IFERROR(G3#/B3#,"") | AB3: =IFERROR(H3#/C3#,"") | AC3: =IFERROR(I3#/D3#,"") | AD3: =IFERROR(J3#/E3#,"") | AE3: =IFERROR(K3#/F3#,"") | AF3: =IFERROR(L3#/B3#,"") | AG3: =IFERROR(M3#/C3#,"") | AH3: =IFERROR(N3#/D3#,"") | AI3: =IFERROR(O3#/E3#,"") | AJ3: =IFERROR(P3#/F3#,"") | AK3: =IFERROR(Q3#/B3#,"") | AL3: =IFERROR(R3#/C3#,"") | AM3: =IFERROR(S3#/D3#,"") | AN3: =IFERROR(T3#/E3#,"") | AO3: =IFERROR(U3#/F3#,"") | AP3: =IFERROR(XLOOKUP($A3#,'[AQ_2020.xlsx]原始数据'!$A:$A,'[AQ_2020.xlsx]原始数据'!$Q:$Q,"")/XLOOKUP($A3#,'[AQ_2020.xlsx]原始数据'!$A:$A,'[AQ_2020.xlsx]原始数据'!$D:$D,""),"") | AQ3: =IFERROR(XLOOKUP($A3#,'[AQ_2021.xlsx]原始数据'!$A:$A,'[AQ_2021.xlsx]原始数据'!$Q:$Q,"")/XLOOKUP($A3#,'[AQ_2021.xlsx]原始数据'!$A:$A,'[AQ_2021.xlsx]原始数据'!$D:$D,""),"") | AR3: =IFERROR(XLOOKUP($A3#,'[AQ_2022.xlsx]原始数据'!$A:$A,'[AQ_2022.xlsx]原始数据'!$Q:$Q,"")/XLOOKUP($A3#,'[AQ_2022.xlsx]原始数据'!$A:$A,'[AQ_2022.xlsx]原始数据'!$D:$D,""),"") | AS3: =IFERROR(XLOOKUP($A3#,'[AQ_2023.xlsx]原始数据'!$A:$A,'[AQ_2023.xlsx]原始数据'!$Q:$Q,"")/XLOOKUP($A3#,'[AQ_2023.xlsx]原始数据'!$A:$A,'[AQ_2023.xlsx]原始数据'!$D:$D,""),"") | AT3: =IFERROR(XLOOKUP($A3#,'[AQ_2024.xlsx]原始数据'!$A:$A,'[AQ_2024.xlsx]原始数据'!$Q:$Q,"")/XLOOKUP($A3#,'[AQ_2024.xlsx]原始数据'!$A:$A,'[AQ_2024.xlsx]原始数据'!$D:$D,""),"")

Sheet 趋势
A1: 指标/年份 | B1: 2020 | C1: 2021 | D1: 2022 | E1: 2023 | F1: 2024
A2: 贷款总额-合计 | B2: =SUM('汇总'!B3#) | C2: =SUM('汇总'!C3#) | D2: =SUM('汇总'!D3#) | E2: =SUM('汇总'!E3#) | F2: =SUM('汇总'!F3#)
A3: 逾期-合计 | B3: =SUM('汇总'!G3#) | C3: =SUM('汇总'!H3#) | D3: =SUM('汇总'!I3#) | E3: =SUM('汇总'!J3#) | F3: =SUM('汇总'!K3#)
A4: 不良-合计 | B4: =SUM('汇总'!L3#) | C4: =SUM('汇总'!M3#) | D4: =SUM('汇总'!N3#) | E4: =SUM('汇总'!O3#) | F4: =SUM('汇总'!P3#)
A5: 关注-合计 | B5: =SUM('汇总'!Q3#) | C5: =SUM('汇总'!R3#) | D5: =SUM('汇总'!S3#) | E5: =SUM('汇总'!T3#) | F5: =SUM('汇总'!U3#)
A6: 新发生不良-合计 | B6: =SUM('汇总'!V3#) | C6: =SUM('汇总'!W3#) | D6: =SUM('汇总'!X3#) | E6: =SUM('汇总'!Y3#) | F6: =SUM('汇总'!Z3#)
A7: 覆盖率-合计 | B7: =IFERROR(SUM(XLOOKUP($A3#,'[AQ_2020.xlsx]原始数据'!$A:$A,'[AQ_2020.xlsx]原始数据'!$Q:$Q))/SUM(XLOOKUP($A3#,'[AQ_2020.xlsx]原始数据'!$A:$A,'[AQ_2020.xlsx]原始数据'!$D:$D)),"") | C7: =IFERROR(SUM(XLOOKUP($A3#,'[AQ_2021.xlsx]原始数据'!$A:$A,'[AQ_2021.xlsx]原始数据'!$Q:$Q))/SUM(XLOOKUP($A3#,'[AQ_2021.xlsx]原始数据'!$A:$A,'[AQ_2021.xlsx]原始数据'!$D:$D)),"") | D7: =IFERROR(SUM(XLOOKUP($A3#,'[AQ_2022.xlsx]原始数据'!$A:$A,'[AQ_2022.xlsx]原始数据'!$Q:$Q))/SUM(XLOOKUP($A3#,'[AQ_2022.xlsx]原始数据'!$A:$A,'[AQ_2022.xlsx]原始数据'!$D:$D)),"") | E7: =IFERROR(SUM(XLOOKUP($A3#,'[AQ_2023.xlsx]原始数据'!$A:$A,'[AQ_2023.xlsx]原始数据'!$Q:$Q))/SUM(XLOOKUP($A3#,'[AQ_2023.xlsx]原始数据'!$A:$A,'[AQ_2023.xlsx]原始数据'!$D:$D)),"") | F7: =IFERROR(SUM(XLOOKUP($A3#,'[AQ_2024.xlsx]原始数据'!$A:$A,'[AQ_2024.xlsx]原始数据'!$Q:$Q))/SUM(XLOOKUP($A3#,'[AQ_2024.xlsx]原始数据'!$A:$A,'[AQ_2024.xlsx]原始数据'!$D:$D)),"")
A8: 逾期率-合计 | B8: =IFERROR(SUM('汇总'!G3#)/SUM('汇总'!B3#),"") | C8: =IFERROR(SUM('汇总'!H3#)/SUM('汇总'!C3#),"") | D8: =IFERROR(SUM('汇总'!I3#)/SUM('汇总'!D3#),"") | E8: =IFERROR(SUM('汇总'!J3#)/SUM('汇总'!E3#),"") | F8: =IFERROR(SUM('汇总'!K3#)/SUM('汇总'!F3#),"")
A9: 不良率-合计 | B9: =IFERROR(SUM('汇总'!L3#)/SUM('汇总'!B3#),"") | C9: =IFERROR(SUM('汇总'!M3#)/SUM('汇总'!C3#),"") | D9: =IFERROR(SUM('汇总'!N3#)/SUM('汇总'!D3#),"") | E9: =IFERROR(SUM('汇总'!O3#)/SUM('汇总'!E3#),"") | F9: =IFERROR(SUM('汇总'!P3#)/SUM('汇总'!F3#),"")

Sheet 分层分析
A1: 年份 | B1: 2024 | D1: 度量 | E1: 不良
A2: 维度 | B2: 行业
A4: 维度值 | B4: 度量合计
A5: =SORT(UNIQUE(IFS($B$2="行业",'[AQ_&$B$1&.xlsx]原始数据'!{v}:{v},$B$2="地区",'[AQ_&$B$1&.xlsx]原始数据'!{v}:{v},$B$2="产品",'[AQ_&$B$1&.xlsx]原始数据'!{v}:{v},$B$2="客户类型",'[AQ_&$B$1&.xlsx]原始数据'!{v}:{v},$B$2="风险分类",'[AQ_&$B$1&.xlsx]原始数据'!{v}:{v},$B$2="IFRS9阶段",'[AQ_&$B$1&.xlsx]原始数据'!{v}:{v},$B$2="担保方式",'[AQ_&$B$1&.xlsx]原始数据'!{v}:{v},$B$2="银行",'[AQ_&$B$1&.xlsx]原始数据'!{v}:{v}))) | B5: =SUMIF(IFS($B$2="行业",'[AQ_&$B$1&.xlsx]原始数据'!{v}:{v},$B$2="地区",'[AQ_&$B$1&.xlsx]原始数据'!{v}:{v},$B$2="产品",'[AQ_&$B$1&.xlsx]原始数据'!{v}:{v},$B$2="客户类型",'[AQ_&$B$1&.xlsx]原始数据'!{v}:{v},$B$2="风险分类",'[AQ_&$B$1&.xlsx]原始数据'!{v}:{v},$B$2="IFRS9阶段",'[AQ_&$B$1&.xlsx]原始数据'!{v}:{v},$B$2="担保方式",'[AQ_&$B$1&.xlsx]原始数据'!{v}:{v},$B$2="银行",'[AQ_&$B$1&.xlsx]原始数据'!{v}:{v}),$A5# ,IFS($E$1="贷款总额",'[AQ_&$B$1&.xlsx]原始数据'!{v}:{v},$E$1="逾期",'[AQ_&$B$1&.xlsx]原始数据'!{v}:{v},$E$1="不良",'[AQ_&$B$1&.xlsx]原始数据'!{v}:{v},$E$1="关注",'[AQ_&$B$1&.xlsx]原始数据'!{v}:{v},$E$1="新发生不良",'[AQ_&$B$1&.xlsx]原始数据'!{v}:{v},$E$1="拨备余额",'[AQ_&$B$1&.xlsx]原始数据'!{v}:{v},$E$1="本期现金回收",'[AQ_&$B$1&.xlsx]原始数据'!{v}:{v},$E$1="本期核销",'[AQ_&$B$1&.xlsx]原始数据'!{v}:{v}))

Sheet 迁徙矩阵
A1: 上期/本期 | B1: 正常 | C1: 关注 | D1: 次级 | E1: 可疑 | F1: 损失
A2: 正常 | B2: =SUMIFS('[AQ_2024.xlsx]原始数据'!$D:$D,'[AQ_2024.xlsx]原始数据'!$L:$L,$A2,'[AQ_2024.xlsx]原始数据'!$K:$K,B$1) | C2: =SUMIFS('[AQ_2024.xlsx]原始数据'!$D:$D,'[AQ_2024.xlsx]原始数据'!$L:$L,$A2,'[AQ_2024.xlsx]原始数据'!$K:$K,C$1) | D2: =SUMIFS('[AQ_2024.xlsx]原始数据'!$D:$D,'[AQ_2024.xlsx]原始数据'!$L:$L,$A2,'[AQ_2024.xlsx]原始数据'!$K:$K,D$1) | E2: =SUMIFS('[AQ_2024.xlsx]原始数据'!$D:$D,'[AQ_2024.xlsx]原始数据'!$L:$L,$A2,'[AQ_2024.xlsx]原始数据'!$K:$K,E$1) | F2: =SUMIFS('[AQ_2024.xlsx]原始数据'!$D:$D,'[AQ_2024.xlsx]原始数据'!$L:$L,$A2,'[AQ_2024.xlsx]原始数据'!$K:$K,F$1)
A3: 关注 | B3: =SUMIFS('[AQ_2024.xlsx]原始数据'!$D:$D,'[AQ_2024.xlsx]原始数据'!$L:$L,$A3,'[AQ_2024.xlsx]原始数据'!$K:$K,B$1) | C3: =SUMIFS('[AQ_2024.xlsx]原始数据'!$D:$D,'[AQ_2024.xlsx]原始数据'!$L:$L,$A3,'[AQ_2024.xlsx]原始数据'!$K:$K,C$1) | D3: =SUMIFS('[AQ_2024.xlsx]原始数据'!$D:$D,'[AQ_2024.xlsx]原始数据'!$L:$L,$A3,'[AQ_2024.xlsx]原始数据'!$K:$K,D$1) | E3: =SUMIFS('[AQ_2024.xlsx]原始数据'!$D:$D,'[AQ_2024.xlsx]原始数据'!$L:$L,$A3,'[AQ_2024.xlsx]原始数据'!$K:$K,E$1) | F3: =SUMIFS('[AQ_2024.xlsx]原始数据'!$D:$D,'[AQ_2024.xlsx]原始数据'!$L:$L,$A3,'[AQ_2024.xlsx]原始数据'!$K:$K,F$1)
A4: 次级 | B4: =SUMIFS('[AQ_2024.xlsx]原始数据'!$D:$D,'[AQ_2024.xlsx]原始数据'!$L:$L,$A4,'[AQ_2024.xlsx]原始数据'!$K:$K,B$1) | C4: =SUMIFS('[AQ_2024.xlsx]原始数据'!$D:$D,'[AQ_2024.xlsx]原始数据'!$L:$L,$A4,'[AQ_2024.xlsx]原始数据'!$K:$K,C$1) | D4: =SUMIFS('[AQ_2024.xlsx]原始数据'!$D:$D,'[AQ_2024.xlsx]原始数据'!$L:$L,$A4,'[AQ_2024.xlsx]原始数据'!$K:$K,D$1) | E4: =SUMIFS('[AQ_2024.xlsx]原始数据'!$D:$D,'[AQ_2024.xlsx]原始数据'!$L:$L,$A4,'[AQ_2024.xlsx]原始数据'!$K:$K,E$1) | F4: =SUMIFS('[AQ_2024.xlsx]原始数据'!$D:$D,'[AQ_2024.xlsx]原始数据'!$L:$L,$A4,'[AQ_2024.xlsx]原始数据'!$K:$K,F$1)
A5: 可疑 | B5: =SUMIFS('[AQ_2024.xlsx]原始数据'!$D:$D,'[AQ_2024.xlsx]原始数据'!$L:$L,$A5,'[AQ_2024.xlsx]原始数据'!$K:$K,B$1) | C5: =SUMIFS('[AQ_2024.xlsx]原始数据'!$D:$D,'[AQ_2024.xlsx]原始数据'!$L:$L,$A5,'[AQ_2024.xlsx]原始数据'!$K:$K,C$1) | D5: =SUMIFS('[AQ_2024.xlsx]原始数据'!$D:$D,'[AQ_2024.xlsx]原始数据'!$L:$L,$A5,'[AQ_2024.xlsx]原始数据'!$K:$K,D$1) | E5: =SUMIFS('[AQ_2024.xlsx]原始数据'!$D:$D,'[AQ_2024.xlsx]原始数据'!$L:$L,$A5,'[AQ_2024.xlsx]原始数据'!$K:$K,E$1) | F5: =SUMIFS('[AQ_2024.xlsx]原始数据'!$D:$D,'[AQ_2024.xlsx]原始数据'!$L:$L,$A5,'[AQ_2024.xlsx]原始数据'!$K:$K,F$1)
A6: 损失 | B6: =SUMIFS('[AQ_2024.xlsx]原始数据'!$D:$D,'[AQ_2024.xlsx]原始数据'!$L:$L,$A6,'[AQ_2024.xlsx]原始数据'!$K:$K,B$1) | C6: =SUMIFS('[AQ_2024.xlsx]原始数据'!$D:$D,'[AQ_2024.xlsx]原始数据'!$L:$L,$A6,'[AQ_2024.xlsx]原始数据'!$K:$K,C$1) | D6: =SUMIFS('[AQ_2024.xlsx]原始数据'!$D:$D,'[AQ_2024.xlsx]原始数据'!$L:$L,$A6,'[AQ_2024.xlsx]原始数据'!$K:$K,D$1) | E6: =SUMIFS('[AQ_2024.xlsx]原始数据'!$D:$D,'[AQ_2024.xlsx]原始数据'!$L:$L,$A6,'[AQ_2024.xlsx]原始数据'!$K:$K,E$1) | F6: =SUMIFS('[AQ_2024.xlsx]原始数据'!$D:$D,'[AQ_2024.xlsx]原始数据'!$L:$L,$A6,'[AQ_2024.xlsx]原始数据'!$K:$K,F$1)

Sheet 拨备与覆盖
A1: 年份 | B1: 2024
A3: 不良余额 | B3: =SUM('[AQ_&B1&.xlsx]原始数据'!$D:$D)
A4: 拨备余额 | B4: =SUM('[AQ_&B1&.xlsx]原始数据'!$Q:$Q)
A5: 覆盖率 | B5: =IFERROR(B4/B3,"")
A6: 成本率(CoR) | B6: =IFERROR((SUM('[AQ_&B1&.xlsx]原始数据'!$R:$R)-SUM('[AQ_&B1&.xlsx]原始数据'!$S:$S))/AVERAGE(SUM('[AQ_&B1&.xlsx]原始数据'!$B:$B),SUM('[AQ_&B1&.xlsx]原始数据'!$B:$B)),"")

Sheet 回收与核销
A1: 年份 | B1: 2024
A3: 核销额 | B3: =SUM('[AQ_&B1&.xlsx]原始数据'!$T:$T)
A4: 现金回收 | B4: =SUM('[AQ_&B1&.xlsx]原始数据'!$U:$U)
A5: 核销率 | B5: =IFERROR(B3/SUM('[AQ_&B1&.xlsx]原始数据'!$D:$D),"")
A6: 回收率 | B6: =IFERROR(B4/(SUM('[AQ_&B1&.xlsx]原始数据'!$D:$D)+SUM('[AQ_&B1&.xlsx]原始数据'!$F:$F)),"")

Sheet 不良桥
A1: 年份 | B1: 2024
A3: 期初不良 | B3: =SUM('[AQ_&B1&.xlsx]原始数据'!$D:$D)-SUM('[AQ_&B1-1&.xlsx]原始数据'!$F:$F)
A4: +新发生不良 | B4: =SUM('[AQ_&B1&.xlsx]原始数据'!$F:$F)
A5: +关注下迁 | B5: =SUMIFS('[AQ_&B1&.xlsx]原始数据'!$D:$D,'[AQ_&B1&.xlsx]原始数据'!$L:$L,"关注",'[AQ_&B1&.xlsx]原始数据'!$K:$K,"不良")
A6: -上迁治愈 | B6: =SUMIFS('[AQ_&B1&.xlsx]原始数据'!$D:$D,'[AQ_&B1&.xlsx]原始数据'!$L:$L,"不良",'[AQ_&B1&.xlsx]原始数据'!$K:$K,"正常")
A7: -核销 | B7: =-SUM('[AQ_&B1&.xlsx]原始数据'!$T:$T)
A8: -现金回收 | B8: =-SUM('[AQ_&B1&.xlsx]原始数据'!$U:$U)
A9: =期末不良 | B9: =SUM('[AQ_&B1&.xlsx]原始数据'!$D:$D)

Sheet 集中度
A1: 年份 | B1: 2024
A3: 维度 | B3: 行业 | D3: 度量 | E3: 贷款总额
A4: 总额 | B4: =SUM(IFS($E$3="贷款总额",'[AQ_&$B$1&.xlsx]原始数据'!$B:$B,$E$3="不良",'[AQ_&$B$1&.xlsx]原始数据'!$D:$D))
A5: 排名 | B5: 名称 | C5: 占比 | D5: 金额
A6: 1 | B6: 制造业 | C6: =IFERROR($D6/$B$4,"") | D6: =SUMIFS('[AQ_&$B$1&.xlsx]原始数据'!$B:$B,'[AQ_&$B$1&.xlsx]原始数据'!$G:$G,$B{row})
A7: 2 | B7: 批发零售 | C7: =IFERROR($D7/$B$4,"") | D7: =SUMIFS('[AQ_&$B$1&.xlsx]原始数据'!$B:$B,'[AQ_&$B$1&.xlsx]原始数据'!$G:$G,$B{row})
A8: 3 | B8: 基建 | C8: =IFERROR($D8/$B$4,"") | D8: =SUMIFS('[AQ_&$B$1&.xlsx]原始数据'!$B:$B,'[AQ_&$B$1&.xlsx]原始数据'!$G:$G,$B{row})
A9: 4 | B9: 房地产 | C9: =IFERROR($D9/$B$4,"") | D9: =SUMIFS('[AQ_&$B$1&.xlsx]原始数据'!$B:$B,'[AQ_&$B$1&.xlsx]原始数据'!$G:$G,$B{row})
A10: 5 | B10: TMT | C10: =IFERROR($D10/$B$4,"") | D10: =SUMIFS('[AQ_&$B$1&.xlsx]原始数据'!$B:$B,'[AQ_&$B$1&.xlsx]原始数据'!$G:$G,$B{row})

Sheet 仪表盘
A1: 仪表盘-关键指标
A3: 不良率(当年) | B3: =IFERROR(INDEX(趋势!B:B, MATCH("不良率-合计",趋势!A:A,0)),"")
A4: 覆盖率(当年) | B4: =IFERROR(INDEX(趋势!B:B, MATCH("覆盖率-合计",趋势!A:A,0)),"")

Sheet 原始数据模板
A1: 银行 | B1: 贷款总额 | C1: 逾期 | D1: 不良 | E1: 关注 | F1: 新发生不良 | G1: 行业 | H1: 地区 | I1: 产品 | J1: 客户类型 | K1: 风险分类 | L1: 上期分类 | M1: IFRS9阶段 | N1: 担保方式 | O1: 抵押物类型 | P1: 抵押物可变现价值 | Q1: 拨备余额 | R1: 本期计提 | S1: 本期转回 | T1: 本期核销 | U1: 本期现金回收 | V1: EAD | W1: PD | X1: LGD
